telegram_upload/__init__.py
telegram_upload/_compat.py
telegram_upload/caption_formatter.py
telegram_upload/cli.py
telegram_upload/config.py
telegram_upload/download_files.py
telegram_upload/exceptions.py
telegram_upload/management.py
telegram_upload/upload_files.py
telegram_upload/utils.py
telegram_upload/video.py
telegram_upload/client/__init__.py
telegram_upload/client/progress_bar.py
telegram_upload/client/telegram_download_client.py
telegram_upload/client/telegram_manager_client.py
telegram_upload/client/telegram_upload_client.py
tests/__init__.py
tests/_compat.py
tests/test_caption_formatter.py
tests/test_cli.py
tests/test_config.py
tests/test_download_files.py
tests/test_exceptions.py
tests/test_files.py
tests/test_management.py
tests/test_upload_files.py
tests/test_utils.py
tests/test_video.py
tests/test_client/__init__.py
tests/test_client/test_progress_bar.py
tests/test_client/test_telegram_download_client.py
tests/test_client/test_telegram_manager_client.py
tests/test_client/test_telegram_upload_client.py
telegram_upload-0.7.1.dist-info/AUTHORS.rst
telegram_upload-0.7.1.dist-info/LICENSE
telegram_upload-0.7.1.dist-info/METADATA
telegram_upload-0.7.1.dist-info/WHEEL
telegram_upload-0.7.1.dist-info/entry_points.txt
telegram_upload-0.7.1.dist-info/top_level.txt
telegram_upload-0.7.1.dist-info/RECORD
