Metadata-Version: 2.1
Name: telegram-upload
Version: 0.7.1
Summary: Upload (and download) files to Telegram up to 4 GiB using your account. 
Home-page: https://github.com/Nekmo/telegram-upload/
Download-URL: https://github.com/Nekmo/telegram-upload/archive/master.zip
Author: Nekmo
Author-email: contacto@nekmo.com
Keywords: telegram-upload,telegram,upload,video
Platform: linux
Classifier: License :: OSI Approved :: MIT License
Classifier: Programming Language :: Python :: 3.8
Classifier: Programming Language :: Python :: 3 :: Only
Classifier: Programming Language :: Python :: 3.9
Classifier: Programming Language :: Python :: 3.7
Classifier: Programming Language :: Python :: 3.10
Classifier: Programming Language :: Python :: 3.11
Classifier: Operating System :: POSIX
Classifier: Operating System :: POSIX :: Linux
Classifier: Natural Language :: English
Classifier: Development Status :: 5 - Production/Stable
Provides: tests
Provides: telegram_upload
License-File: LICENSE
License-File: AUTHORS.rst
